coldxrayPy.py
coldxrayPy-1.1.0.dist-info/METADATA
coldxrayPy-1.1.0.dist-info/WHEEL
coldxrayPy-1.1.0.dist-info/top_level.txt
coldxrayPy-1.1.0.dist-info/RECORD
