Metadata-Version: 2.1
Name: coldxrayPy
Version: 1.1.0
Summary: cold x-ray material effects package
